mobilex/__init__.py
mobilex/cache/__init__.py
mobilex/cache/base.py
mobilex/cache/dict.py
mobilex/cache/redis.py
mobilex/const.py
mobilex/core.py
mobilex/exc.py
mobilex/responses.py
mobilex/router.py
mobilex/screens/__init__.py
mobilex/screens/base.py
mobilex/sessions.py
mobilex/utils/__init__.py
mobilex/utils/types.py
mobilex-0.0.5.dist-info/LICENSE.txt
mobilex-0.0.5.dist-info/METADATA
mobilex-0.0.5.dist-info/WHEEL
mobilex-0.0.5.dist-info/RECORD
