Metadata-Version: 2.1
Name: mobilex
Version: 0.0.5
Summary: USSD and SMS exchange framework
Home-page: https://github.com/davidkyalo/python-mobilex
License: MIT
Keywords: mobilex,mobile,USSD,SMS
Author: David Kyalo
Author-email: davidmkyalo@gmail.com
Requires-Python: >=3.10,<4.0
Classifier: License :: OSI Approved :: MIT License
Classifier: Programming Language :: Python :: 3
Classifier: Programming Language :: Python :: 3.10
Classifier: Programming Language :: Python :: 3.11
Requires-Dist: phonenumbers (>=8.12.51,<9.0.0)
Requires-Dist: redis (>=4.5.5,<5.0.0)
Requires-Dist: typing-extensions (>=4.1.1,<5.0.0)
Project-URL: Documentation, https://davidkyalo.github.io/python-mobilex
Project-URL: Repository, https://github.com/davidkyalo/python-mobilex
